sqlite3i/__init__.py
sqlite3i-0.0.2.dist-info/LICENSE
sqlite3i-0.0.2.dist-info/METADATA
sqlite3i-0.0.2.dist-info/WHEEL
sqlite3i-0.0.2.dist-info/top_level.txt
sqlite3i-0.0.2.dist-info/RECORD
